{
  "name": "头部关注",
  "author": "r-markdown",
  "category": "引导",
  "subCategory": "",
  "description": "所有颜色可自己调整",
  "date": "2026-07-18",
  "content": "<!-- 素材开始 -->\n<container height=\"50px\" padding=\"0px\" margin=\"20px 0\" bg=\"#27ae60\" border-style=\"none\" radius=\"50px\" direction=\"row\" align=\"start-center\">\n<svg xmlns=\"http://www.w3.org/2000/svg\" viewBox=\"0 0 48 48\" width=\"48\" height=\"48\" style=\"margin-left:20px\">\n  <g fill=\"none\" stroke=\"#ffffff\" stroke-width=\"4.5\"\n     stroke-linecap=\"round\" stroke-linejoin=\"round\">\n    <path d=\"M24 36 L24 16 M24 16 L14 26 M24 16 L34 26\" opacity=\"0.4\">\n      <animateTransform attributeName=\"transform\" type=\"translate\"\n        values=\"0,8; 0,8; 0,-8; 0,-8; 0,8\"\n        dur=\"1.2s\" repeatCount=\"indefinite\"/>\n      <animate attributeName=\"opacity\"\n        values=\"0.4; 1; 1; 0.4; 0.4\"\n        dur=\"1.2s\" repeatCount=\"indefinite\"/>\n    </path>\n  </g>\n</svg>\n<container width=\"\" height=\"40px\" padding=\"0px\" margin=\"0px 5px 0 20px\" bg=\"#ffffff\" border-style=\"none\" radius=\"50px\" direction=\"row\" align=\"center-center\" extra-style=\"flex-grow:1\">\n<text>点击上方</text>\n<text color=\"#028af2\" weight=\"600\">「蓝字」</text>\n<text>关注我们</text>\n</conatiner>\n</container>\n<!-- 素材结束 -->"
}
